mcp_oauth2/__init__.py
mcp_oauth2/config.py
mcp_oauth2/exceptions.py
mcp_oauth2/middleware.py
mcp_oauth2/models.py
mcp_oauth2/token_validation.py
mcp_oauth2/utils.py
mcp_oauth2-0.1.0.dist-info/METADATA
mcp_oauth2-0.1.0.dist-info/WHEEL
mcp_oauth2-0.1.0.dist-info/licenses/LICENSE
mcp_oauth2-0.1.0.dist-info/RECORD
